{"id":"eca70101-6829-9878-66dd-da7fbc7a98d4","name":"Alfresco REST API Blog - Part 9 - Queries & Search","description":"","order":["99ca80f9-1e3e-e75d-e685-b262b9ccd73a","68b58305-6570-7f2b-3777-420cb67f656b","4f67b77b-e03e-29d7-011e-d09f87654ad6","06f118d4-8148-9301-3283-11148875185b","bf288848-34dd-bbf7-929d-701da3cac1cf","ccb090a3-2617-d5ce-8716-4144dbd27713","3e8a0ea6-6d7d-0124-55d1-da1514ad72f6","56c0480e-8694-55ca-365f-664250153dfd","2599152c-6906-70a6-1a8c-0c35b44b27d0","af769eec-e669-35ec-3e43-fd61f84d0c57","449823b7-de87-7630-a442-e0f90618710b","6a014f2f-1deb-e8e0-3159-146c1162357c"],"folders":[],"timestamp":1491814570007,"owner":"250102","public":false,"requests":[{"id":"06f118d4-8148-9301-3283-11148875185b","headers":"Authorization: Basic dGVzdDp0ZXN0\n","url":"http:\/\/localhost:8080\/alfresco\/api\/-default-\/public\/alfresco\/versions\/1\/queries\/nodes?term=lorem","preRequestScript":"","pathVariables":[],"method":"GET","data":[],"dataMode":"params","version":2,"tests":"","currentHelper":"normal","helperAttributes":[],"time":1491832215050,"name":"Nodes query","description":"","collectionId":"eca70101-6829-9878-66dd-da7fbc7a98d4","responses":[]},{"id":"2599152c-6906-70a6-1a8c-0c35b44b27d0","headers":"Content-Type: application\/json\nAuthorization: Basic dGVzdDp0ZXN0\n","url":"http:\/\/localhost:8080\/alfresco\/api\/-default-\/public\/search\/versions\/1\/search","preRequestScript":null,"pathVariables":[],"method":"POST","data":[],"dataMode":"raw","tests":null,"currentHelper":"normal","helperAttributes":[],"time":1491823546490,"name":"Basic Lucene search","description":"","collectionId":"eca70101-6829-9878-66dd-da7fbc7a98d4","responses":[],"rawModeData":"{\n  \"query\": {\n    \"query\": \"+@cm\\\\:modified:[NOW\/DAY-7DAYS TO NOW\/DAY+1DAY] +TYPE:\\\"cm:content\\\"\",\n    \"language\": \"lucene\"\n  }\n}\n"},{"id":"3e8a0ea6-6d7d-0124-55d1-da1514ad72f6","headers":"Content-Type: application\/json\nAuthorization: Basic dGVzdDp0ZXN0\n","url":"http:\/\/localhost:8080\/alfresco\/api\/-default-\/public\/search\/versions\/1\/search","preRequestScript":null,"pathVariables":[],"method":"POST","data":[],"dataMode":"raw","tests":null,"currentHelper":"normal","helperAttributes":[],"time":1491836483537,"name":"Basic search","description":"","collectionId":"eca70101-6829-9878-66dd-da7fbc7a98d4","responses":[],"rawModeData":"{\n  \"query\": {\n    \"query\": \"lorem\"\n  }\n}\n"},{"id":"449823b7-de87-7630-a442-e0f90618710b","headers":"Content-Type: application\/json\nAuthorization: Basic dGVzdDp0ZXN0\n","url":"http:\/\/localhost:8080\/alfresco\/api\/-default-\/public\/search\/versions\/1\/search","preRequestScript":null,"pathVariables":[],"method":"POST","data":[],"dataMode":"raw","tests":null,"currentHelper":"normal","helperAttributes":[],"time":1491898852832,"name":"Search with facets","description":"","collectionId":"eca70101-6829-9878-66dd-da7fbc7a98d4","responses":[],"rawModeData":"{\n  \"query\": {\n    \"query\": \"(name:\\\"test*\\\" OR title:\\\"test*\\\") AND TYPE:\\\"cm:content\\\"\"\n  },\n  \"facetQueries\": [\n    {\"query\": \"content.size:[0 TO 10240]\", \"label\": \"Small Files\"},\n    {\"query\": \"content.mimetype:'text\/plain'\", \"label\": \"Plain Text\"},\n    {\"query\": \"content.mimetype:'image\/jpeg' OR content.mimetype:'image\/png' OR content.mimetype:'image\/gif'\", \"label\": \"Images\"},\n    {\"query\": \"content.mimetype:'application\/msword' OR content.mimetype:'application\/vnd.ms-excel'\", \"label\": \"Office\"}\n  ], \n  \"facetFields\": {\"facets\": [{\"field\": \"creator\"}]}\n}\n"},{"id":"4f67b77b-e03e-29d7-011e-d09f87654ad6","headers":"Authorization: Basic dGVzdDp0ZXN0\n","url":"http:\/\/localhost:8080\/alfresco\/api\/-default-\/public\/alfresco\/versions\/1\/nodes\/{{siteContainerId}}\/children","preRequestScript":"","pathVariables":[],"method":"POST","data":[{"key":"filedata","value":"test-lorem-ipsum.txt","type":"file","enabled":true}],"dataMode":"params","version":2,"tests":"","currentHelper":"normal","helperAttributes":[],"time":1491815599611,"name":"Upload file","description":"","collectionId":"eca70101-6829-9878-66dd-da7fbc7a98d4","responses":[]},{"id":"56c0480e-8694-55ca-365f-664250153dfd","headers":"Content-Type: application\/json\nAuthorization: Basic dGVzdDp0ZXN0\n","url":"http:\/\/localhost:8080\/alfresco\/api\/-default-\/public\/search\/versions\/1\/search","preRequestScript":null,"pathVariables":[],"method":"POST","data":[],"dataMode":"raw","tests":null,"currentHelper":"normal","helperAttributes":[],"time":1491819704448,"name":"Basic CMIS search","description":"","collectionId":"eca70101-6829-9878-66dd-da7fbc7a98d4","responses":[],"rawModeData":"{\n  \"query\": {\n    \"query\": \"select * from cmis:document WHERE cmis:name LIKE 'test.%'\",\n    \"language\": \"cmis\"\n  }\n}\n"},{"id":"68b58305-6570-7f2b-3777-420cb67f656b","headers":"Authorization: Basic dGVzdDp0ZXN0\n","url":"http:\/\/localhost:8080\/alfresco\/api\/-default-\/public\/alfresco\/versions\/1\/sites\/queriesSearchSite\/containers\/documentLibrary","preRequestScript":"","pathVariables":[],"method":"GET","data":[],"dataMode":"params","version":2,"tests":"postman.setGlobalVariable('siteContainerId', JSON.parse(responseBody).entry.id);","currentHelper":"normal","helperAttributes":[],"time":1491814826508,"name":"Retrieve document library container","description":"","collectionId":"eca70101-6829-9878-66dd-da7fbc7a98d4","responses":[]},{"id":"6a014f2f-1deb-e8e0-3159-146c1162357c","headers":"Content-Type: application\/json\nAuthorization: Basic dGVzdDp0ZXN0\n","url":"http:\/\/localhost:8080\/alfresco\/api\/-default-\/public\/search\/versions\/1\/search","preRequestScript":null,"pathVariables":[],"method":"POST","data":[],"dataMode":"raw","tests":null,"currentHelper":"normal","helperAttributes":[],"time":1491898881080,"name":"Search with term highlighting","description":"","collectionId":"eca70101-6829-9878-66dd-da7fbc7a98d4","responses":[],"rawModeData":"{\n  \"query\": {\n    \"query\": \"(name:\\\"test*\\\" OR title:\\\"test*\\\") AND TYPE:\\\"cm:content\\\"\"\n  },\n  \"highlight\": {\n    \"fields\": [\n      {\n        \"field\": \"cm:name\",\n        \"prefix\": \"(\",\n        \"postfix\": \")\"\n      },\n      {\n        \"field\": \"{http:\/\/www.alfresco.org\/model\/content\/1.0}title\"\n      }\n    ]\n  }\n}\n"},{"id":"99ca80f9-1e3e-e75d-e685-b262b9ccd73a","headers":"Authorization: Basic dGVzdDp0ZXN0\nContent-Type: application\/json\n","url":"http:\/\/localhost:8080\/alfresco\/api\/-default-\/public\/alfresco\/versions\/1\/sites","preRequestScript":"","pathVariables":[],"method":"POST","data":[],"dataMode":"raw","version":2,"tests":"","currentHelper":"normal","helperAttributes":[],"time":1491814704567,"name":"Create public site","description":"","collectionId":"eca70101-6829-9878-66dd-da7fbc7a98d4","responses":[],"rawModeData":"{\n  \"id\": \"queriesSearchSite\",\n  \"title\": \"Queries and Search Site\",\n  \"description\": \"Site created for queries and search blog post\",\n  \"visibility\": \"PUBLIC\"\n}"},{"id":"af769eec-e669-35ec-3e43-fd61f84d0c57","headers":"Content-Type: application\/json\nAuthorization: Basic dGVzdDp0ZXN0\n","url":"http:\/\/localhost:8080\/alfresco\/api\/-default-\/public\/search\/versions\/1\/search","preRequestScript":null,"pathVariables":[],"method":"POST","data":[],"dataMode":"raw","tests":null,"currentHelper":"normal","helperAttributes":[],"time":1491820619233,"name":"Search with paging and sorting","description":"","collectionId":"eca70101-6829-9878-66dd-da7fbc7a98d4","responses":[],"rawModeData":"{\n  \"query\": {\n    \"query\": \"+TYPE:\\\"cm:content\\\"\",\n    \"language\": \"afts\"\n  },\n  \"paging\": {\n    \"maxItems\": \"25\",\n    \"skipCount\": \"10\"\n  },\n  \"sort\": [{\"type\":\"FIELD\", \"field\":\"cm:name\", \"ascending\":\"false\"}]\n}\n"},{"id":"bf288848-34dd-bbf7-929d-701da3cac1cf","headers":"Authorization: Basic dGVzdDp0ZXN0\n","url":"http:\/\/localhost:8080\/alfresco\/api\/-default-\/public\/alfresco\/versions\/1\/queries\/sites?term=queries","preRequestScript":"","pathVariables":[],"method":"GET","data":[],"dataMode":"params","version":2,"tests":"","currentHelper":"normal","helperAttributes":[],"time":1491819027369,"name":"Sites query","description":"","collectionId":"eca70101-6829-9878-66dd-da7fbc7a98d4","responses":[]},{"id":"ccb090a3-2617-d5ce-8716-4144dbd27713","headers":"Authorization: Basic dGVzdDp0ZXN0\n","url":"http:\/\/localhost:8080\/alfresco\/api\/-default-\/public\/alfresco\/versions\/1\/queries\/people?term=jackson","preRequestScript":"","pathVariables":[],"method":"GET","data":[],"dataMode":"params","version":2,"tests":"","currentHelper":"normal","helperAttributes":[],"time":1491819193299,"name":"People query","description":"","collectionId":"eca70101-6829-9878-66dd-da7fbc7a98d4","responses":[]}]}